chaosgcp/__init__.py
chaosgcp/apphub/__init__.py
chaosgcp/apphub/actions.py
chaosgcp/artifact/__init__.py
chaosgcp/artifact/probes.py
chaosgcp/cloudbuild/__init__.py
chaosgcp/cloudbuild/actions.py
chaosgcp/cloudbuild/probes.py
chaosgcp/cloudlogging/__init__.py
chaosgcp/cloudlogging/controls/__init__.py
chaosgcp/cloudlogging/controls/journal.py
chaosgcp/cloudlogging/probes.py
chaosgcp/cloudrun/__init__.py
chaosgcp/cloudrun/actions.py
chaosgcp/cloudrun/probes.py
chaosgcp/compute/__init__.py
chaosgcp/compute/actions.py
chaosgcp/dns/__init__.py
chaosgcp/dns/actions.py
chaosgcp/gke/__init__.py
chaosgcp/gke/nodepool/__init__.py
chaosgcp/gke/nodepool/actions.py
chaosgcp/gke/nodepool/probes.py
chaosgcp/iam/__init__.py
chaosgcp/iam/controls/__init__.py
chaosgcp/iam/controls/policy.md
chaosgcp/iam/controls/policy.py
chaosgcp/lb/__init__.py
chaosgcp/lb/actions.py
chaosgcp/lb/probes.py
chaosgcp/monitoring/__init__.py
chaosgcp/monitoring/probes.py
chaosgcp/neg/__init__.py
chaosgcp/neg/actions.py
chaosgcp/neg/probes.py
chaosgcp/networkconnectivity/__init__.py
chaosgcp/networkconnectivity/actions.py
chaosgcp/sql/__init__.py
chaosgcp/sql/actions.py
chaosgcp/sql/probes.py
chaosgcp/storage/__init__.py
chaosgcp/storage/probes.py
chaosgcp/types.py
chaostoolkit_google_cloud_platform-0.37.0.dist-info/METADATA
chaostoolkit_google_cloud_platform-0.37.0.dist-info/WHEEL
chaostoolkit_google_cloud_platform-0.37.0.dist-info/licenses/LICENSE
chaostoolkit_google_cloud_platform-0.37.0.dist-info/RECORD
