Metadata-Version: 2.1
Name: chaostoolkit-google-cloud-platform
Version: 0.37.0
Summary: Google Cloud Platform extension for the Chaos Toolkit
Author-Email: Chaos Toolkit <contact@chaostoolkit.org>, Sylvain Hellegouarch <sh@defuze.org>
License: Apache-2.0
Classifier: Development Status :: 5 - Production/Stable
Classifier: Intended Audience :: Developers
Classifier: License :: Freely Distributable
Classifier: License :: OSI Approved :: Apache Software License
Classifier: Operating System :: OS Independent
Classifier: Programming Language :: Python
Classifier: Programming Language :: Python :: 3
Classifier: Programming Language :: Python :: 3.8
Classifier: Programming Language :: Python :: 3.9
Classifier: Programming Language :: Python :: 3.10
Classifier: Programming Language :: Python :: 3.11
Classifier: Programming Language :: Python :: 3.12
Classifier: Programming Language :: Python :: Implementation
Classifier: Programming Language :: Python :: Implementation :: CPython
Project-URL: Homepage, https://chaostoolkit.org/
Project-URL: Repository, https://github.com/chaostoolkit-incubator/chaostoolkit-google-cloud-platform
Project-URL: Documentation, https://chaostoolkit.org/drivers/gcp/
Project-URL: Changelog, https://github.com/chaostoolkit-incubator/chaostoolkit-google-cloud-platform/blob/main/CHANGELOG.md
Requires-Python: >=3.8
Requires-Dist: google-auth>=2.28.0
Requires-Dist: google-auth-httplib2>=0.2.0
Requires-Dist: google-api-python-client>=2.118.0
Requires-Dist: google-cloud-storage>=2.14.0
Requires-Dist: google-cloud-run>=0.10.3
Requires-Dist: google-cloud-container>=2.40.0
Requires-Dist: google-cloud-logging>=3.9.0
Requires-Dist: google-cloud-monitoring>=2.19.1
Requires-Dist: google-cloud-artifact-registry>=1.11.1
Requires-Dist: google-cloud-containeranalysis>=2.14.1
Requires-Dist: google-cloud-compute>=1.16.1
Requires-Dist: google-cloud-network-connectivity>=2.4.2
Requires-Dist: dateparser>=1.2.0
Requires-Dist: grafeas>=1.9.1
Requires-Dist: chaostoolkit-kubernetes>=0.34.1
Requires-Dist: chaostoolkit-lib>=1.43.0
Requires-Dist: google-cloud-apphub>=0.1.0
Requires-Dist: google-cloud-resource-manager>=1.12.3
Provides-Extra: lueur
